goshstore-0.3.0.dist-info/metadata.json
goshstore-0.3.0.dist-info/top_level.txt
goshstore-0.3.0.dist-info/WHEEL
goshstore-0.3.0.dist-info/DESCRIPTION.rst
goshstore-0.3.0.dist-info/RECORD
goshstore-0.3.0.dist-info/METADATA
goshstore/__init__.py
goshstore/fields.py
