Metadata-Version: 2.0
Name: goshstore
Version: 0.3.0
Summary: Django get-or-set hstore field
Home-page: https://github.com/conanfanli/goshstore
Author: Conan Fan Li
Author-email: conanlics@gmail.com
License: MIT
Keywords: django hstore postgres
Platform: UNKNOWN
Classifier: Development Status :: 3 - Alpha
Classifier: License :: OSI Approved :: MIT License
Classifier: Programming Language :: Python :: 3.4
Requires-Dist: django (<=1.9.1,>=1.9.0)
Provides-Extra: dev
Requires-Dist: psycopg2 (==2.6.1); extra == 'dev'
Requires-Dist: coverage (==4.0.2); extra == 'dev'
